meshagent/__init__.py
meshagent/version.py
meshagent-0.25.1.dist-info/licenses/LICENSE
meshagent-0.25.1.dist-info/METADATA
meshagent-0.25.1.dist-info/WHEEL
meshagent-0.25.1.dist-info/top_level.txt
meshagent-0.25.1.dist-info/RECORD
