Metadata-Version: 2.4
Name: meshagent
Version: 0.25.1
Summary: Meshagent
License-Expression: Apache-2.0
Project-URL: Documentation, https://docs.meshagent.com
Project-URL: Website, https://www.meshagent.com
Project-URL: Source, https://www.meshagent.com
Requires-Python: >=3.13
License-File: LICENSE
Provides-Extra: all
Requires-Dist: meshagent-api[all]~=0.25.1; extra == "all"
Requires-Dist: meshagent-agents[all]~=0.25.1; extra == "all"
Requires-Dist: meshagent-cli[all]~=0.25.1; extra == "all"
Requires-Dist: meshagent-computers~=0.25.1; extra == "all"
Requires-Dist: meshagent-livekit~=0.25.1; extra == "all"
Requires-Dist: meshagent-mcp~=0.25.1; extra == "all"
Requires-Dist: meshagent-openai~=0.25.1; extra == "all"
Requires-Dist: meshagent-anthropic~=0.25.1; extra == "all"
Requires-Dist: meshagent-otel~=0.25.1; extra == "all"
Requires-Dist: meshagent-tools~=0.25.1; extra == "all"
Provides-Extra: agents
Requires-Dist: meshagent-agents[all]~=0.25.1; extra == "agents"
Provides-Extra: tools
Requires-Dist: meshagent-tools~=0.25.1; extra == "tools"
Provides-Extra: cli
Requires-Dist: meshagent-cli[all]~=0.25.1; extra == "cli"
Provides-Extra: mcp-service
Requires-Dist: meshagent-cli[mcp-service]~=0.25.1; extra == "mcp-service"
Provides-Extra: otel
Requires-Dist: meshagent-otel~=0.25.1; extra == "otel"
Dynamic: license-file
